nicecal/__init__.py
nicecal-1.1.3.dist-info/DESCRIPTION.rst
nicecal-1.1.3.dist-info/METADATA
nicecal-1.1.3.dist-info/RECORD
nicecal-1.1.3.dist-info/WHEEL
nicecal-1.1.3.dist-info/metadata.json
nicecal-1.1.3.dist-info/top_level.txt
