Metadata-Version: 2.0
Name: nicecal
Version: 1.1.3
Summary: Create good looking plain text calendars using box-drawing characters.
Home-page: https://github.com/awesmubarak/nicecal
Author: Awes Mubarak
Author-email: awes.mubarak@awesmubarak.com
License: MIT
Keywords: nicecal calendar cal unicode
Platform: UNKNOWN
Classifier: Development Status :: 5 - Production/Stable
Classifier: Intended Audience :: End Users/Desktop
Classifier: Operating System :: OS Independent
Classifier: Topic :: Utilities
Classifier: License :: OSI Approved :: MIT License
Classifier: Programming Language :: Python
